{
    "created_time": "2021-03-23T04:01:40Z",
    "files": [
        {
            "attachment_folder": "",
            "created_time": "2021-05-01T11:15:57Z",
            "id": "420",
            "modified_time": "2021-08-05T06:23:40Z",
            "name": "广西综合概况.md",
            "signature": "56098203636405",
            "tags": [
            ]
        },
        {
            "attachment_folder": "",
            "created_time": "2021-05-01T11:22:12Z",
            "id": "421",
            "modified_time": "2022-01-28T12:10:33Z",
            "name": "南宁市.md",
            "signature": "60908567007925",
            "tags": [
            ]
        },
        {
            "attachment_folder": "",
            "created_time": "2021-05-01T11:22:27Z",
            "id": "422",
            "modified_time": "2022-01-28T15:27:55Z",
            "name": "柳州市.md",
            "signature": "133158506861237",
            "tags": [
            ]
        },
        {
            "attachment_folder": "",
            "created_time": "2021-05-01T11:22:42Z",
            "id": "423",
            "modified_time": "2022-01-28T12:09:40Z",
            "name": "桂林市.md",
            "signature": "117821178647221",
            "tags": [
            ]
        },
        {
            "attachment_folder": "",
            "created_time": "2021-05-01T11:22:57Z",
            "id": "424",
            "modified_time": "2022-01-28T12:08:57Z",
            "name": "梧州市.md",
            "signature": "75185038299829",
            "tags": [
            ]
        },
        {
            "attachment_folder": "",
            "created_time": "2021-05-01T11:23:14Z",
            "id": "425",
            "modified_time": "2022-01-28T13:01:20Z",
            "name": "北海市.md",
            "signature": "118512668381877",
            "tags": [
            ]
        },
        {
            "attachment_folder": "",
            "created_time": "2021-05-01T11:23:32Z",
            "id": "426",
            "modified_time": "2022-01-28T12:08:31Z",
            "name": "防城港市.md",
            "signature": "97604767584949",
            "tags": [
            ]
        },
        {
            "attachment_folder": "",
            "created_time": "2021-05-01T11:23:46Z",
            "id": "427",
            "modified_time": "2022-01-28T12:08:20Z",
            "name": "钦州市.md",
            "signature": "55969354617525",
            "tags": [
            ]
        },
        {
            "attachment_folder": "",
            "created_time": "2021-05-01T11:24:00Z",
            "id": "428",
            "modified_time": "2022-01-28T12:08:11Z",
            "name": "贵港市.md",
            "signature": "36474498060981",
            "tags": [
            ]
        },
        {
            "attachment_folder": "",
            "created_time": "2021-05-01T11:24:14Z",
            "id": "429",
            "modified_time": "2022-01-28T12:07:54Z",
            "name": "玉林市.md",
            "signature": "611521139381",
            "tags": [
            ]
        },
        {
            "attachment_folder": "",
            "created_time": "2021-05-01T11:24:28Z",
            "id": "430",
            "modified_time": "2022-01-28T15:25:26Z",
            "name": "百色市.md",
            "signature": "73969562555061",
            "tags": [
            ]
        },
        {
            "attachment_folder": "",
            "created_time": "2021-05-01T11:24:42Z",
            "id": "431",
            "modified_time": "2022-01-28T12:51:54Z",
            "name": "贺州市.md",
            "signature": "134373982606005",
            "tags": [
            ]
        },
        {
            "attachment_folder": "",
            "created_time": "2021-05-01T11:24:57Z",
            "id": "432",
            "modified_time": "2022-01-28T12:07:15Z",
            "name": "河池市.md",
            "signature": "56111088538293",
            "tags": [
            ]
        },
        {
            "attachment_folder": "",
            "created_time": "2021-05-01T11:25:10Z",
            "id": "433",
            "modified_time": "2022-01-28T12:06:52Z",
            "name": "来宾市.md",
            "signature": "33931877421749",
            "tags": [
            ]
        },
        {
            "attachment_folder": "",
            "created_time": "2021-05-01T11:25:25Z",
            "id": "434",
            "modified_time": "2022-01-29T05:45:01Z",
            "name": "崇左市.md",
            "signature": "82409173291701",
            "tags": [
            ]
        }
    ],
    "folders": [
    ],
    "id": "419",
    "modified_time": "2021-03-23T04:01:40Z",
    "signature": "35907562377909",
    "version": 3
}
