{
    "created_time": "2021-03-31T11:56:11Z",
    "files": [
        {
            "attachment_folder": "",
            "created_time": "2021-03-31T11:56:26Z",
            "id": "822",
            "modified_time": "2022-02-03T03:49:34Z",
            "name": "各地特色产品.md",
            "signature": "107685055828668",
            "tags": [
            ]
        },
        {
            "attachment_folder": "",
            "created_time": "2021-03-31T11:58:42Z",
            "id": "823",
            "modified_time": "2022-02-03T03:49:44Z",
            "name": "著名特色用品.md",
            "signature": "87730637771452",
            "tags": [
            ]
        },
        {
            "attachment_folder": "",
            "created_time": "2021-03-31T11:59:15Z",
            "id": "824",
            "modified_time": "2022-02-03T03:49:55Z",
            "name": "著名特点纪念品.md",
            "signature": "62733928108732",
            "tags": [
            ]
        },
        {
            "attachment_folder": "",
            "created_time": "2021-03-31T11:59:50Z",
            "id": "825",
            "modified_time": "2022-02-03T03:50:04Z",
            "name": "各地土特产一览表.md",
            "signature": "112413814821564",
            "tags": [
            ]
        }
    ],
    "folders": [
    ],
    "id": "821",
    "modified_time": "2021-03-31T11:56:11Z",
    "signature": "104923391857340",
    "version": 3
}
