{
    "created_time": "2021-03-23T04:03:15Z",
    "files": [
        {
            "attachment_folder": "",
            "created_time": "2021-05-01T13:45:59Z",
            "id": "568",
            "modified_time": "2025-07-22T07:55:41Z",
            "name": "兰州市.md",
            "signature": "127205682188983",
            "tags": [
            ]
        },
        {
            "attachment_folder": "",
            "created_time": "2021-05-01T13:46:23Z",
            "id": "569",
            "modified_time": "2025-07-22T07:53:27Z",
            "name": "嘉峪关市.md",
            "signature": "43432345080503",
            "tags": [
            ]
        },
        {
            "attachment_folder": "",
            "created_time": "2021-05-01T13:46:40Z",
            "id": "570",
            "modified_time": "2025-06-30T15:22:21Z",
            "name": "金昌市.md",
            "signature": "54620734886583",
            "tags": [
            ]
        },
        {
            "attachment_folder": "",
            "created_time": "2021-05-01T13:47:39Z",
            "id": "574",
            "modified_time": "2025-06-30T15:21:52Z",
            "name": "白银市.md",
            "signature": "104897622053559",
            "tags": [
            ]
        },
        {
            "attachment_folder": "",
            "created_time": "2021-05-01T13:47:54Z",
            "id": "575",
            "modified_time": "2025-10-21T07:33:09Z",
            "name": "天水市.md",
            "signature": "103634901668535",
            "tags": [
            ]
        },
        {
            "attachment_folder": "",
            "created_time": "2021-05-01T13:47:25Z",
            "id": "573",
            "modified_time": "2025-07-22T07:56:03Z",
            "name": "武威市.md",
            "signature": "103256944546487",
            "tags": [
            ]
        },
        {
            "attachment_folder": "",
            "created_time": "2021-05-01T13:47:09Z",
            "id": "572",
            "modified_time": "2025-07-23T16:48:06Z",
            "name": "张掖市.md",
            "signature": "49758831907511",
            "tags": [
            ]
        },
        {
            "attachment_folder": "",
            "created_time": "2021-05-01T13:48:11Z",
            "id": "576",
            "modified_time": "2025-06-30T15:19:42Z",
            "name": "平凉市.md",
            "signature": "104064398398135",
            "tags": [
            ]
        },
        {
            "attachment_folder": "",
            "created_time": "2021-05-01T13:46:55Z",
            "id": "571",
            "modified_time": "2025-08-25T07:29:45Z",
            "name": "酒泉市.md",
            "signature": "80300344349367",
            "tags": [
            ]
        },
        {
            "attachment_folder": "",
            "created_time": "2021-05-01T13:48:25Z",
            "id": "577",
            "modified_time": "2025-06-30T15:18:04Z",
            "name": "庆阳市.md",
            "signature": "19608161489591",
            "tags": [
            ]
        },
        {
            "attachment_folder": "",
            "created_time": "2021-05-01T13:48:40Z",
            "id": "578",
            "modified_time": "2025-06-30T15:17:33Z",
            "name": "定西市.md",
            "signature": "28172326277815",
            "tags": [
            ]
        },
        {
            "attachment_folder": "",
            "created_time": "2021-05-01T13:48:55Z",
            "id": "579",
            "modified_time": "2025-06-30T15:16:50Z",
            "name": "陇南市.md",
            "signature": "38364283671223",
            "tags": [
            ]
        },
        {
            "attachment_folder": "",
            "created_time": "2021-05-01T13:49:29Z",
            "id": "581",
            "modified_time": "2025-06-30T15:16:15Z",
            "name": "临夏回族自治州.md",
            "signature": "128227884405431",
            "tags": [
            ]
        },
        {
            "attachment_folder": "",
            "created_time": "2021-05-01T13:49:14Z",
            "id": "580",
            "modified_time": "2025-11-11T11:13:18Z",
            "name": "甘南藏族自治州.md",
            "signature": "95762226614967",
            "tags": [
            ]
        },
        {
            "attachment_folder": "",
            "created_time": "2021-05-01T13:49:47Z",
            "id": "582",
            "modified_time": "2023-04-27T09:12:03Z",
            "name": "兰州新区.md",
            "signature": "51768876602039",
            "tags": [
            ]
        }
    ],
    "folders": [
        {
            "name": "解读甘肃"
        }
    ],
    "id": "1305",
    "modified_time": "2021-03-23T04:03:15Z",
    "signature": "72852871058103",
    "version": 3
}
